pslmw_md_toc_files/__init__.py
pslmw_md_toc_files/logger_config.py
pslmw_md_toc_files/pslmw_md_toc_files.py
pslmw_md_toc_files-1.0.0.dist-info/licenses/LICENSE
pslmw_md_toc_files-1.0.0.dist-info/METADATA
pslmw_md_toc_files-1.0.0.dist-info/WHEEL
pslmw_md_toc_files-1.0.0.dist-info/top_level.txt
pslmw_md_toc_files-1.0.0.dist-info/RECORD
