Metadata-Version: 2.4
Name: pslmw-md-toc-files
Version: 1.0.0
Summary: pslmw-md-toc-files is a python tool for creating a `TOC` content from the .md file inside of it.
Author-email: Emili Garriga Coll <porsilasmocasweb@gmail.com>
Maintainer-email: Emili Garriga Coll <porsilasmocasweb@gmail.com>
License: The MIT License (MIT)
Project-URL: Repository, https://github.com/porsilasmoscasweb/pslmw-md-toc-files
Project-URL: Bug Tracker, https://github.com/porsilasmoscasweb/pslmw-md-toc-files/issues
Keywords: markdown,sort,organization,TOC,md,index,files
Classifier: Development Status :: 5 - Production/Stable
Classifier: Programming Language :: Python :: 3
Requires-Python: >=3.9
License-File: LICENSE
Requires-Dist: pslmw-md-toc
Provides-Extra: test
Requires-Dist: pytest; extra == "test"
Dynamic: license-file
